quinten_graph/__init__.py
quinten_graph/config.py
quinten_graph/plotting.py
quinten_graph/settings.py
quinten_graph/utils.py
quinten_graph-0.1.1.dist-info/LICENSE.txt
quinten_graph-0.1.1.dist-info/METADATA
quinten_graph-0.1.1.dist-info/WHEEL
quinten_graph-0.1.1.dist-info/top_level.txt
quinten_graph-0.1.1.dist-info/RECORD
