Metadata-Version: 2.1
Name: quinten-graph
Version: 0.1.1
Summary: Package to standardize and facilitate plotting settings
Author-email: Vincent-Paul Vincentelli <v.vincentelli@quinten-france.com>
Project-URL: Homepage, https://gitlab.par.quinten.io/qf/quinten_graph
Project-URL: Bug Tracker, https://gitlab.par.quinten.io/qf/quinten_graph/-/issues
Classifier: Programming Language :: Python :: 3
Classifier: License :: OSI Approved :: MIT License
Classifier: Operating System :: OS Independent
Requires-Python: >=3.7
License-File: LICENSE.txt
Requires-Dist: numpy
Requires-Dist: pandas
Requires-Dist: matplotlib
Requires-Dist: seaborn
